{
  "tickets": [
    {
      "id": "bf8c",
      "title": "23к",
      "body": "к23к"
    },
    {
      "id": "5bb3",
      "title": "3к23к",
      "body": "32к23к"
    },
    {
      "id": "953c",
      "title": "екрекр",
      "body": "екрекр"
    },
    {
      "id": "c53e",
      "title": "керекр",
      "body": "керекр"
    },
    {
      "id": "4238",
      "title": "керекркер",
      "body": "екркерк"
    },
    {
      "id": "1d2b",
      "title": "керекркер",
      "body": "керке"
    },
    {
      "id": "dbf5",
      "title": "екрекр",
      "body": "екркер"
    },
    {
      "id": "b646",
      "title": "екркер",
      "body": "екркер"
    }
  ]
}